proj_init/__init__.py
proj_init/create.py
proj_init-1.0.5.dist-info/entry_points.txt
proj_init-1.0.5.dist-info/LICENSE
proj_init-1.0.5.dist-info/WHEEL
proj_init-1.0.5.dist-info/METADATA
proj_init-1.0.5.dist-info/RECORD
