Metadata-Version: 2.1
Name: proj-init
Version: 1.0.5
Summary: Initialize you github projects with a one liner
Home-page: https://github.com/thalesnunes/gcal_notifier
License: MIT
Author: Thales Nunes
Author-email: thalesaknunes22@gmail.com
Requires-Python: >=3.6.2,<4.0.0
Classifier: License :: OSI Approved :: MIT License
Classifier: Programming Language :: Python
Classifier: Programming Language :: Python :: 3
Classifier: Programming Language :: Python :: 3.10
Classifier: Programming Language :: Python :: 3.6
Classifier: Programming Language :: Python :: 3.7
Classifier: Programming Language :: Python :: 3.8
Classifier: Programming Language :: Python :: 3.9
Requires-Dist: PyGithub (>=1.55,<2.0)
Project-URL: Repository, https://github.com/thalesnunes/gcal_notifier
